pysimplendi.cpython-38-darwin.so
pysimplendi-0.1.3.dist-info/LICENSE.md
pysimplendi-0.1.3.dist-info/METADATA
pysimplendi-0.1.3.dist-info/WHEEL
pysimplendi-0.1.3.dist-info/top_level.txt
pysimplendi-0.1.3.dist-info/RECORD
