Metadata-Version: 2.1
Name: pysimplendi
Version: 0.1.3
Summary: simple python NDI sender/receiver
Home-page: https://github.com/73-ch/pySimpleNDI
Author: Kosaku Namikawa
Author-email: cigarbox.nami@gmail.com
License: MIT
Platform: UNKNOWN
Requires-Dist: setuptools
Requires-Dist: wheel
Requires-Dist: pybind11 (==2.6.0)
